setup.py
src/infi/__init__.py
src/infi.dtypes.hctl.egg-info/PKG-INFO
src/infi.dtypes.hctl.egg-info/SOURCES.txt
src/infi.dtypes.hctl.egg-info/dependency_links.txt
src/infi.dtypes.hctl.egg-info/entry_points.txt
src/infi.dtypes.hctl.egg-info/namespace_packages.txt
src/infi.dtypes.hctl.egg-info/not-zip-safe
src/infi.dtypes.hctl.egg-info/top_level.txt
src/infi/dtypes/__init__.py
src/infi/dtypes/hctl/__init__.py
src/infi/dtypes/hctl/__version__.py