Metadata-Version: 1.1
Name: infi.dtypes.hctl
Version: 0.0.7
Summary: HCTL-related datatypes in Python
Home-page: https://github.com/Infinidat/infi.dtypes.hctl
Author: Tal Yalon
Author-email: tal.yalon@gmail.com
License: PSF
Platform: UNKNOWN
Classifier: Intended Audience :: Developers
Classifier: Intended Audience :: System Administrators
Classifier: License :: OSI Approved :: Python Software Foundation License
Classifier: Operating System :: OS Independent
Classifier: Programming Language :: Python
Classifier: Topic :: Software Development :: Libraries :: Python Modules
